MANIFEST.in
README.md
setup.py
cellworld_game/README.md
cellworld_game/__init__.py
cellworld_game/agent.py
cellworld_game/cellworld_loader.py
cellworld_game/coordinate_converter.py
cellworld_game/event.py
cellworld_game/interfaces.py
cellworld_game/lib.py
cellworld_game/license.txt
cellworld_game/line_of_sight.py
cellworld_game/log.py
cellworld_game/model.py
cellworld_game/mouse.py
cellworld_game/navigation.py
cellworld_game/navigation_agent.py
cellworld_game/points.py
cellworld_game/polygon.py
cellworld_game/resources.py
cellworld_game/robot.py
cellworld_game/setup.cfg
cellworld_game/util.py
cellworld_game/video.py
cellworld_game/view.py
cellworld_game/visibility.py
cellworld_game.egg-info/PKG-INFO
cellworld_game.egg-info/SOURCES.txt
cellworld_game.egg-info/dependency_links.txt
cellworld_game.egg-info/not-zip-safe
cellworld_game.egg-info/requires.txt
cellworld_game.egg-info/top_level.txt
cellworld_game/__pycache__/__init__.cpython-312.pyc
cellworld_game/__pycache__/agent.cpython-312.pyc
cellworld_game/__pycache__/cellworld_loader.cpython-312.pyc
cellworld_game/__pycache__/coordinate_converter.cpython-312.pyc
cellworld_game/__pycache__/event.cpython-312.pyc
cellworld_game/__pycache__/interfaces.cpython-312.pyc
cellworld_game/__pycache__/lib.cpython-312.pyc
cellworld_game/__pycache__/line_of_sight.cpython-312.pyc
cellworld_game/__pycache__/log.cpython-312.pyc
cellworld_game/__pycache__/model.cpython-312.pyc
cellworld_game/__pycache__/mouse.cpython-312.pyc
cellworld_game/__pycache__/navigation.cpython-312.pyc
cellworld_game/__pycache__/navigation_agent.cpython-312.pyc
cellworld_game/__pycache__/points.cpython-312.pyc
cellworld_game/__pycache__/polygon.cpython-312.pyc
cellworld_game/__pycache__/resources.cpython-312.pyc
cellworld_game/__pycache__/robot.cpython-312.pyc
cellworld_game/__pycache__/util.cpython-312.pyc
cellworld_game/__pycache__/video.cpython-312.pyc
cellworld_game/__pycache__/view.cpython-312.pyc
cellworld_game/__pycache__/visibility.cpython-312.pyc
cellworld_game/files/agent.png
cellworld_game/files/predator.png
cellworld_game/files/prey.png
cellworld_game/shapely/__init__.py
cellworld_game/shapely/geometry.py
cellworld_game/shapely/points.py
