Metadata-Version: 2.1
Name: cellworld_game
Version: 0.0.190
Summary: Simulation environment for the cellworld research platform
Home-page: https://github.com/germanespinosa/cellworld_game
Author: German Espinosa
Author-email: germanespinosa@gmail.com
License: MIT
Requires-Dist: cellworld
Requires-Dist: pygame
Requires-Dist: shapely
Requires-Dist: pulsekit
